bkup/main - 副本.py
mcp_miaocontrol_v6-0.1.6.dist-info/METADATA
mcp_miaocontrol_v6-0.1.6.dist-info/WHEEL
mcp_miaocontrol_v6-0.1.6.dist-info/entry_points.txt
mcp_miaocontrol_v6-0.1.6.dist-info/top_level.txt
mcp_miaocontrol_v6-0.1.6.dist-info/RECORD
